UnicodeEmoji/__init__.py
UnicodeEmoji/emoji.json
UnicodeEmoji-0.0.2.dist-info/METADATA
UnicodeEmoji-0.0.2.dist-info/WHEEL
UnicodeEmoji-0.0.2.dist-info/top_level.txt
UnicodeEmoji-0.0.2.dist-info/RECORD
