Metadata-Version: 2.1
Name: UnicodeEmoji
Version: 0.0.2
Summary: Provides all Unicode Emojis as an enum.
Author-email: Daan Knoope <daan@knoope.dev>
License: MIT
Keywords: emoji
Requires-Python: >=3.6
